
{
  "header": {
    "reportVersion": 1,
    "event": "Allocation failed - JavaScript heap out of memory",
    "trigger": "FatalError",
    "filename": "report.20210401.232958.8460.0.001.json",
    "dumpEventTime": "2021-04-01T23:29:58Z",
    "dumpEventTimeStamp": "1617319798953",
    "processId": 8460,
    "cwd": "C:\\Users\\alidu\\OneDrive\\Desktop\\front-dater",
    "commandLine": [
      "C:\\Program Files\\nodejs\\node.exe",
      "C:\\Users\\alidu\\OneDrive\\Desktop\\front-dater\\node_modules\\.bin\\\\..\\next\\dist\\bin\\next",
      "dev"
    ],
    "nodejsVersion": "v12.8.1",
    "wordSize": 64,
    "arch": "x64",
    "platform": "win32",
    "componentVersions": {
      "node": "12.8.1",
      "v8": "7.5.288.22-node.16",
      "uv": "1.30.1",
      "zlib": "1.2.11",
      "brotli": "1.0.7",
      "ares": "1.15.0",
      "modules": "72",
      "nghttp2": "1.39.2",
      "napi": "4",
      "llhttp": "1.1.4",
      "http_parser": "2.8.0",
      "openssl": "1.1.1c",
      "cldr": "35.1",
      "icu": "64.2",
      "tz": "2019a",
      "unicode": "12.1"
    },
    "release": {
      "name": "node",
      "headersUrl": "https://nodejs.org/download/release/v12.8.1/node-v12.8.1-headers.tar.gz",
      "sourceUrl": "https://nodejs.org/download/release/v12.8.1/node-v12.8.1.tar.gz",
      "libUrl": "https://nodejs.org/download/release/v12.8.1/win-x64/node.lib"
    },
    "osName": "Windows_NT",
    "osRelease": "10.0.17763",
    "osVersion": "Windows 10 Pro",
    "osMachine": "x86_64",
    "cpus": [
      {
        "model": "Intel(R) Celeron(R) CPU B815 @ 1.60GHz",
        "speed": 1596,
        "user": 17747359,
        "nice": 0,
        "sys": 8832578,
        "idle": 41841609,
        "irq": 356312
      },
      {
        "model": "Intel(R) Celeron(R) CPU B815 @ 1.60GHz",
        "speed": 1596,
        "user": 18768265,
        "nice": 0,
        "sys": 8225593,
        "idle": 41427296,
        "irq": 79218
      }
    ],
    "networkInterfaces": [
      {
        "name": "Wi-Fi",
        "internal": false,
        "mac": "64:27:37:e2:98:61",
        "address": "fe80::e0df:ad4:8e39:a809",
        "netmask": "ffff:ffff:ffff:ffff::",
        "family": "IPv6",
        "scopeid": 16
      },
      {
        "name": "Wi-Fi",
        "internal": false,
        "mac": "64:27:37:e2:98:61",
        "address": "10.18.174.72",
        "netmask": "255.255.252.0",
        "family": "IPv4"
      },
      {
        "name": "Loopback Pseudo-Interface 1",
        "internal": true,
        "mac": "00:00:00:00:00:00",
        "address": "::1",
        "netmask": "ffff:ffff:ffff:ffff:ffff:ffff:ffff:ffff",
        "family": "IPv6",
        "scopeid": 0
      },
      {
        "name": "Loopback Pseudo-Interface 1",
        "internal": true,
        "mac": "00:00:00:00:00:00",
        "address": "127.0.0.1",
        "netmask": "255.0.0.0",
        "family": "IPv4"
      }
    ],
    "host": "DESKTOP-FKR6RIH"
  },
  "javascriptStack": {
    "message": "No stack.",
    "stack": [
      "Unavailable."
    ]
  },
  "nativeStack": [
    {
      "pc": "0x00007ff719f76de9",
      "symbol": "std::basic_ostream<char,std::char_traits<char> >::operator<<+10873"
    },
    {
      "pc": "0x00007ff719f7b3dc",
      "symbol": "std::basic_ostream<char,std::char_traits<char> >::operator<<+28780"
    },
    {
      "pc": "0x00007ff719f7a388",
      "symbol": "std::basic_ostream<char,std::char_traits<char> >::operator<<+24600"
    },
    {
      "pc": "0x00007ff71a065a9b",
      "symbol": "v8::base::CPU::has_sse+37691"
    },
    {
      "pc": "0x00007ff71a84c90e",
      "symbol": "v8::Isolate::ReportExternalAllocationLimitReached+94"
    },
    {
      "pc": "0x00007ff71a834c5a",
      "symbol": "v8::SharedArrayBuffer::Externalize+842"
    },
    {
      "pc": "0x00007ff71a6c636c",
      "symbol": "v8::internal::Heap::EphemeronKeyWriteBarrierFromCode+1436"
    },
    {
      "pc": "0x00007ff71a6ce28f",
      "symbol": "v8::internal::Heap::OldGenerationSizeOfObjects+4879"
    },
    {
      "pc": "0x00007ff71a6c4533",
      "symbol": "v8::internal::Heap::CollectGarbage+1235"
    },
    {
      "pc": "0x00007ff71a6c2dc4",
      "symbol": "v8::internal::Heap::AddRetainedMap+2292"
    },
    {
      "pc": "0x00007ff71a6e18a5",
      "symbol": "v8::internal::Factory::NewFillerObject+53"
    },
    {
      "pc": "0x00007ff71a497c1d",
      "symbol": "v8::internal::interpreter::JumpTableTargetOffsets::iterator::operator=+3757"
    },
    {
      "pc": "0x00007ff71ac6bd9d",
      "symbol": "v8::internal::SetupIsolateDelegate::SetupHeap+614605"
    },
    {
      "pc": "0x0000032d1572c89f",
      "symbol": ""
    }
  ],
  "javascriptHeap": {
    "totalMemory": 2152132608,
    "totalCommittedMemory": 2152132608,
    "usedMemory": 2122951920,
    "availableMemory": 47951256,
    "memoryLimit": 2197815296,
    "heapSpaces": {
      "read_only_space": {
        "memorySize": 262144,
        "committedMemory": 262144,
        "capacity": 261832,
        "used": 31960,
        "available": 229872
      },
      "new_space": {
        "memorySize": 2097152,
        "committedMemory": 2097152,
        "capacity": 1047328,
        "used": 162040,
        "available": 885288
      },
      "old_space": {
        "memorySize": 1193422848,
        "committedMemory": 1193422848,
        "capacity": 1173214232,
        "used": 1173108152,
        "available": 106080
      },
      "code_space": {
        "memorySize": 3833856,
        "committedMemory": 3833856,
        "capacity": 3056608,
        "used": 3056608,
        "available": 0
      },
      "map_space": {
        "memorySize": 10752000,
        "committedMemory": 10752000,
        "capacity": 5945520,
        "used": 5945520,
        "available": 0
      },
      "large_object_space": {
        "memorySize": 940568576,
        "committedMemory": 940568576,
        "capacity": 939550392,
        "used": 939550392,
        "available": 0
      },
      "code_large_object_space": {
        "memorySize": 1196032,
        "committedMemory": 1196032,
        "capacity": 1097248,
        "used": 1097248,
        "available": 0
      },
      "new_large_object_space": {
        "memorySize": 0,
        "committedMemory": 0,
        "capacity": 1047328,
        "used": 0,
        "available": 1047328
      }
    }
  },
  "resourceUsage": {
    "userCpuSeconds": 3390.23,
    "kernelCpuSeconds": 209.281,
    "cpuConsumptionPercent": 18.8951,
    "maxRss": 1902030848,
    "pageFaults": {
      "IORequired": 21639935,
      "IONotRequired": 0
    },
    "fsActivity": {
      "reads": 48355,
      "writes": 2633
    }
  },
  "libuv": [
  ],
  "environmentVariables": {
    "=C:": "C:\\Users\\alidu\\OneDrive\\Desktop\\front-dater",
    "ALLUSERSPROFILE": "C:\\ProgramData",
    "ANDROID_HOME": "C:\\Users\\alidu\\AppData\\Local\\Android\\Sdk",
    "APPDATA": "C:\\Users\\alidu\\AppData\\Roaming",
    "asl.log=Destination": "file",
    "ChocolateyInstall": "C:\\ProgramData\\chocolatey",
    "ChocolateyLastPathUpdate": "132104739864590763",
    "CLASSPATH": ".;",
    "CommonProgramFiles": "C:\\Program Files\\Common Files",
    "CommonProgramFiles(x86)": "C:\\Program Files (x86)\\Common Files",
    "CommonProgramW6432": "C:\\Program Files\\Common Files",
    "COMPUTERNAME": "DESKTOP-FKR6RIH",
    "ComSpec": "C:\\Windows\\system32\\cmd.exe",
    "DriverData": "C:\\Windows\\System32\\Drivers\\DriverData",
    "FPS_BROWSER_APP_PROFILE_STRING": "Internet Explorer",
    "FPS_BROWSER_USER_PROFILE_STRING": "Default",
    "HOMEDRIVE": "C:",
    "HOMEPATH": "\\Users\\alidu",
    "INIT_CWD": "C:\\Users\\alidu\\OneDrive\\Desktop\\front-dater",
    "JAVA_HOME": "C:\\Program Files\\Java\\jdk1.8.0_221",
    "LOCALAPPDATA": "C:\\Users\\alidu\\AppData\\Local",
    "LOGONSERVER": "\\\\DESKTOP-FKR6RIH",
    "NODE": "C:\\Program Files\\nodejs\\node.exe",
    "NODE_ENV": "development",
    "npm_config_argv": "{\"remain\":[],\"cooked\":[\"run\",\"dev\"],\"original\":[\"dev\"]}",
    "npm_config_bin_links": "true",
    "npm_config_ignore_optional": "",
    "npm_config_ignore_scripts": "",
    "npm_config_init_license": "MIT",
    "npm_config_init_version": "1.0.0",
    "npm_config_registry": "https://registry.yarnpkg.com",
    "npm_config_save_prefix": "^",
    "npm_config_strict_ssl": "true",
    "npm_config_user_agent": "yarn/1.22.4 npm/? node/v12.8.1 win32 x64",
    "npm_config_version_commit_hooks": "true",
    "npm_config_version_git_message": "v%s",
    "npm_config_version_git_sign": "",
    "npm_config_version_git_tag": "true",
    "npm_config_version_tag_prefix": "v",
    "npm_execpath": "C:\\Program Files (x86)\\Yarn\\bin\\yarn.js",
    "npm_lifecycle_event": "dev",
    "npm_lifecycle_script": "next dev",
    "npm_node_execpath": "C:\\Program Files\\nodejs\\node.exe",
    "npm_package_dependencies_aos": "^3.0.0-beta.6",
    "npm_package_dependencies_axios": "^0.21.1",
    "npm_package_dependencies_bootstrap": "^4.6.0",
    "npm_package_dependencies_css_loader": "^5.1.3",
    "npm_package_dependencies_dotenv": "^8.2.0",
    "npm_package_dependencies_laravel_echo": "^1.10.0",
    "npm_package_dependencies_next": "10.0.9",
    "npm_package_dependencies_next_redux_wrapper": "^6.0.2",
    "npm_package_dependencies_nprogress": "^0.2.0",
    "npm_package_dependencies_pusher_js": "^7.0.3",
    "npm_package_dependencies_react": "17.0.1",
    "npm_package_dependencies_react_chat_window": "^1.2.1",
    "npm_package_dependencies_react_cropper": "^2.1.7",
    "npm_package_dependencies_react_dom": "17.0.1",
    "npm_package_dependencies_react_hook_form": "^6.15.4",
    "npm_package_dependencies_react_hook_form_resolvers": "^0.0.1",
    "npm_package_dependencies_react_icons": "^4.2.0",
    "npm_package_dependencies_react_loading_skeleton": "^2.2.0",
    "npm_package_dependencies_react_moment": "^1.1.1",
    "npm_package_dependencies_react_notify_toast": "^0.5.1",
    "npm_package_dependencies_react_paginate": "^7.1.0",
    "npm_package_dependencies_react_pure_loaders": "^3.0.1",
    "npm_package_dependencies_react_redux": "^7.2.2",
    "npm_package_dependencies_react_select": "^4.2.1",
    "npm_package_dependencies_redux": "^4.0.5",
    "npm_package_dependencies_sass": "^1.32.8",
    "npm_package_dependencies_sass_loader": "^11.0.1",
    "npm_package_dependencies_socket_io_client": "^4.0.0",
    "npm_package_dependencies_style_loader": "^2.0.0",
    "npm_package_dependencies_sweetalert2": "^10.15.6",
    "npm_package_dependencies_universal_cookie": "^4.0.4",
    "npm_package_dependencies_yup": "^0.32.9",
    "npm_package_dependencies__hookform_resolvers": "0.1.0",
    "npm_package_dependencies__reduxjs_toolkit": "^1.5.0",
    "npm_package_description": "First, run the development server:",
    "npm_package_name": "front-dater",
    "npm_package_private": "true",
    "npm_package_readmeFilename": "README.md",
    "npm_package_scripts_build": "next build",
    "npm_package_scripts_dev": "next dev",
    "npm_package_scripts_start": "next start",
    "npm_package_version": "0.1.0",
    "NUMBER_OF_PROCESSORS": "2",
    "OneDrive": "C:\\Users\\alidu\\OneDrive",
    "OS": "Windows_NT",
    "Path": "C:\\Users\\alidu\\AppData\\Local\\Temp\\yarn--1617300784314-0.5065210214558531;C:\\Users\\alidu\\OneDrive\\Desktop\\front-dater\\node_modules\\.bin;C:\\Users\\alidu\\AppData\\Local\\Yarn\\Data\\link\\node_modules\\.bin;C:\\Program Files\\libexec\\lib\\node_modules\\npm\\bin\\node-gyp-bin;C:\\Program Files\\lib\\node_modules\\npm\\bin\\node-gyp-bin;C:\\Program Files\\nodejs\\node_modules\\npm\\bin\\node-gyp-bin;C:\\Windows\\system32;C:\\Windows;C:\\Windows\\System32\\Wbem;C:\\Windows\\System32\\WindowsPowerShell\\v1.0\\;C:\\Windows\\System32\\OpenSSH\\;C:\\xampp\\php;C:\\Program Files\\Git\\cmd;C:\\ProgramData\\chocolatey\\bin;C:\\Program Files\\nodejs\\;C:\\Program Files\\Java\\jdk1.8.0_221\\bin;C:\\composer;C:\\Program Files\\PuTTY\\;C:\\Program Files (x86)\\Yarn\\bin\\;c:\\Users\\alidu\\AppData\\Local\\Android\\Sdk\\platform-tools;C:\\Users\\alidu\\AppData\\Local\\Programs\\Microsoft VS Code\\bin;C:\\Users\\alidu\\AppData\\Roaming\\npm;C:\\Program Files\\heroku\\bin;C:\\Users\\alidu\\AppData\\Roaming\\Composer\\vendor\\bin;C:\\Users\\alidu\\AppData\\Local\\Yarn\\bin",
    "PATHEXT": ".COM;.EXE;.BAT;.CMD;.VBS;.VBE;.JSE;.WSF;.WSH;.MSC",
    "php": "C:\\xampp\\php",
    "PROCESSOR_ARCHITECTURE": "AMD64",
    "PROCESSOR_IDENTIFIER": "Intel64 Family 6 Model 42 Stepping 7, GenuineIntel",
    "PROCESSOR_LEVEL": "6",
    "PROCESSOR_REVISION": "2a07",
    "ProgramData": "C:\\ProgramData",
    "ProgramFiles": "C:\\Program Files",
    "ProgramFiles(x86)": "C:\\Program Files (x86)",
    "ProgramW6432": "C:\\Program Files",
    "PROMPT": "$P$G",
    "PSModulePath": "C:\\Program Files\\WindowsPowerShell\\Modules;C:\\Windows\\system32\\WindowsPowerShell\\v1.0\\Modules",
    "PUBLIC": "C:\\Users\\Public",
    "SESSIONNAME": "Console",
    "SystemDrive": "C:",
    "SystemRoot": "C:\\Windows",
    "TEMP": "C:\\Users\\alidu\\AppData\\Local\\Temp",
    "TMP": "C:\\Users\\alidu\\AppData\\Local\\Temp",
    "TRACE_ID": "aa68d0749d99fefa",
    "USERDOMAIN": "DESKTOP-FKR6RIH",
    "USERDOMAIN_ROAMINGPROFILE": "DESKTOP-FKR6RIH",
    "USERNAME": "alidu",
    "USERPROFILE": "C:\\Users\\alidu",
    "windir": "C:\\Windows",
    "YARN_WRAP_OUTPUT": "false"
  },
  "sharedObjects": [
    "C:\\Program Files\\nodejs\\node.exe",
    "C:\\Windows\\SYSTEM32\\ntdll.dll",
    "C:\\Windows\\System32\\KERNEL32.DLL",
    "C:\\Windows\\System32\\KERNELBASE.dll",
    "C:\\Windows\\System32\\WS2_32.dll",
    "C:\\Windows\\System32\\RPCRT4.dll",
    "C:\\Windows\\System32\\ADVAPI32.dll",
    "C:\\Windows\\System32\\msvcrt.dll",
    "C:\\Windows\\System32\\sechost.dll",
    "C:\\Windows\\System32\\USER32.dll",
    "C:\\Windows\\System32\\win32u.dll",
    "C:\\Windows\\System32\\GDI32.dll",
    "C:\\Windows\\SYSTEM32\\dbghelp.dll",
    "C:\\Windows\\System32\\gdi32full.dll",
    "C:\\Windows\\System32\\ucrtbase.dll",
    "C:\\Windows\\System32\\msvcp_win.dll",
    "C:\\Windows\\System32\\PSAPI.DLL",
    "C:\\Windows\\System32\\CRYPT32.dll",
    "C:\\Windows\\System32\\MSASN1.dll",
    "C:\\Windows\\System32\\bcrypt.dll",
    "C:\\Windows\\SYSTEM32\\IPHLPAPI.DLL",
    "C:\\Windows\\SYSTEM32\\USERENV.dll",
    "C:\\Windows\\System32\\profapi.dll",
    "C:\\Windows\\SYSTEM32\\WINMM.dll",
    "C:\\Windows\\SYSTEM32\\winmmbase.dll",
    "C:\\Windows\\System32\\cfgmgr32.dll",
    "C:\\Windows\\System32\\IMM32.DLL",
    "C:\\Windows\\System32\\powrprof.dll",
    "C:\\Windows\\system32\\uxtheme.dll",
    "C:\\Windows\\System32\\combase.dll",
    "C:\\Windows\\System32\\bcryptPrimitives.dll",
    "C:\\Windows\\system32\\mswsock.dll",
    "C:\\Windows\\System32\\kernel.appcore.dll",
    "C:\\Windows\\SYSTEM32\\CRYPTBASE.DLL",
    "C:\\Windows\\System32\\NSI.dll",
    "C:\\Windows\\SYSTEM32\\dhcpcsvc6.DLL",
    "C:\\Windows\\SYSTEM32\\dhcpcsvc.DLL",
    "C:\\Windows\\SYSTEM32\\DNSAPI.dll",
    "C:\\Program Files\\Bonjour\\mdnsNSP.dll",
    "C:\\Windows\\System32\\rasadhlp.dll",
    "C:\\Windows\\System32\\fwpuclnt.dll",
    "C:\\Windows\\system32\\napinsp.dll",
    "C:\\Windows\\system32\\pnrpnsp.dll",
    "C:\\Windows\\System32\\winrnr.dll",
    "C:\\Windows\\system32\\NLAapi.dll",
    "C:\\Windows\\system32\\wshbth.dll"
  ]
}